mm_agent_search_mcp_server/__init__.py
mm_agent_search_mcp_server/server.py
mm_agent_search_mcp_server-0.1.3.dist-info/METADATA
mm_agent_search_mcp_server-0.1.3.dist-info/WHEEL
mm_agent_search_mcp_server-0.1.3.dist-info/entry_points.txt
mm_agent_search_mcp_server-0.1.3.dist-info/top_level.txt
mm_agent_search_mcp_server-0.1.3.dist-info/RECORD
