Metadata-Version: 2.4
Name: mm-agent-search-mcp-server
Version: 0.1.3
Summary: Add your description here
Requires-Python: >=3.12
Requires-Dist: mcp>=1.9.1
Requires-Dist: requests>=2.32.3
